scrapai/__init__.py
scrapai/code_generator.py
scrapai/scrapai_client.py
scrapai/ai_agent/__init__.py
scrapai/ai_agent/agent.py
scrapai/ai_analyzer/__init__.py
scrapai/ai_analyzer/analyzer.py
scrapai/ai_analyzer/api_finder.py
scrapai/ai_analyzer/system_prompt.py
scrapai/ai_analyzer/xml_parser.py
scrapai/ai_scraper/__init__.py
scrapai/ai_scraper/data_parser.py
scrapai/ai_scraper/scraper.py
scrapai/ai_scraper/system_prompt.py
scrapai/ai_services/__init__.py
scrapai/ai_services/config.py
scrapai/ai_services/registry.py
scrapai/ai_tools/__init__.py
scrapai/ai_tools/config_runner.py
scrapai/ai_tools/response_validator.py
scrapai/ai_tools/tools.py
scrapai/ai_tools/url_tester.py
scrapai/config/__init__.py
scrapai/config/manager.py
scrapai/config/proxy_manager.py
scrapai/config/proxy_schema.py
scrapai/config/schema.py
scrapai/crawler/__init__.py
scrapai/crawler/execution_engine.py
scrapai/crawler/resource_processor.py
scrapai/utils/__init__.py
scrapai/utils/browser_client.py
scrapai/utils/data_transformer.py
scrapai/utils/html_extractor.py
scrapai/utils/http_client.py
scrapai-0.5.1.dist-info/METADATA
scrapai-0.5.1.dist-info/WHEEL
scrapai-0.5.1.dist-info/top_level.txt
scrapai-0.5.1.dist-info/RECORD
