Metadata-Version: 2.4
Name: scrapai
Version: 0.5.1
Summary: AI-powered web scraping SDK with intelligent configuration generation
Home-page: https://github.com/zohaib3249/scrapai
Author: Zohaib Yousaf
Author-email: chzohaib136@gmail.com
License: MIT
Project-URL: Bug Reports, https://github.com/zohaib3249/scrapai/issues
Project-URL: Source, https://github.com/zohaib3249/scrapai
Project-URL: Documentation, https://github.com/zohaib3249/scrapai#readme
Keywords: web-scraping,ai,scraping,automation,data-extraction,scraping-sdk,ai-agent,web-crawler
Classifier: Development Status :: 3 - Alpha
Classifier: Intended Audience :: Developers
Classifier: License :: OSI Approved :: MIT License
Classifier: Programming Language :: Python :: 3
Classifier: Programming Language :: Python :: 3.8
Classifier: Programming Language :: Python :: 3.9
Classifier: Programming Language :: Python :: 3.10
Classifier: Programming Language :: Python :: 3.11
Classifier: Programming Language :: Python :: 3.12
Classifier: Topic :: Software Development :: Libraries :: Python Modules
Classifier: Topic :: Internet :: WWW/HTTP :: Indexing/Search
Requires-Python: >=3.8
Requires-Dist: requests>=2.32.5
Requires-Dist: urllib3>=2.5.0
Requires-Dist: beautifulsoup4>=4.14.2
Requires-Dist: lxml>=6.0.2
Requires-Dist: fake-useragent>=2.2.0
Requires-Dist: openai>=2.6.1
Requires-Dist: playwright>=1.55.0
Requires-Dist: playwright-stealth>=2.0.0
Provides-Extra: playwright
Requires-Dist: playwright>=1.55.0; extra == "playwright"
Requires-Dist: playwright-stealth>=2.0.0; extra == "playwright"
Provides-Extra: all
Requires-Dist: playwright>=1.55.0; extra == "all"
Requires-Dist: playwright-stealth>=2.0.0; extra == "all"
Dynamic: author
Dynamic: author-email
Dynamic: classifier
Dynamic: description
Dynamic: description-content-type
Dynamic: home-page
Dynamic: keywords
Dynamic: license
Dynamic: project-url
Dynamic: provides-extra
Dynamic: requires-dist
Dynamic: requires-python
Dynamic: summary
